sara/__init__.py
sara/ext.py
sara/nsfw.py
sara/req.py
sara/reqNh.py
sara/rolplay.py
sara/rolplayNsfw.py
sara/sfw.py
saraapi-1.3.0.dist-info/LICENSE
saraapi-1.3.0.dist-info/METADATA
saraapi-1.3.0.dist-info/WHEEL
saraapi-1.3.0.dist-info/top_level.txt
saraapi-1.3.0.dist-info/RECORD
